resourcemanager/__init__.py
resourcemanager/constants.py
resourcemanager/handlers.py
resourcemanager/manager.py
resourcemanager/resourceclasses.py
resourcemanager-0.0.3.dist-info/DESCRIPTION.rst
resourcemanager-0.0.3.dist-info/METADATA
resourcemanager-0.0.3.dist-info/RECORD
resourcemanager-0.0.3.dist-info/WHEEL
resourcemanager-0.0.3.dist-info/metadata.json
resourcemanager-0.0.3.dist-info/top_level.txt
