Metadata-Version: 2.0
Name: resourcemanager
Version: 0.0.3
Summary: A resource manager for Python programs
Home-page: https://github.com/brandonmpace/resourcemanager
Author: Brandon M. Pace
Author-email: brandonmpace@gmail.com
License: GNU Lesser General Public License v3 or later
Keywords: resource file update manager
Platform: any
Classifier: Development Status :: 2 - Pre-Alpha
Classifier: License :: OSI Approved :: GNU Lesser General Public License v3 or later (LGPLv3+)
Classifier: Operating System :: OS Independent
Classifier: Programming Language :: Python :: 3
Requires-Python: >=3.6.5
